<?xml version="1.0" encoding="UTF-8"?><record_update table="ua_table_licensing_config">
    <ua_table_licensing_config action="INSERT_OR_UPDATE">
        <is_fulfillment>false</is_fulfillment>
        <license_condition/>
        <license_model>none</license_model>
        <license_roles/>
        <name>x_g_ni4_interdivis_cutoff_date</name>
        <op_delete>true</op_delete>
        <op_insert>true</op_insert>
        <op_update>true</op_update>
        <owner_condition/>
        <sys_class_name>ua_table_licensing_config</sys_class_name>
        <sys_created_by>jnz1202</sys_created_by>
        <sys_created_on>2021-02-23 18:12:20</sys_created_on>
        <sys_customer_update>false</sys_customer_update>
        <sys_id>1efd054d1b2a6c508418ebddac4bcbed</sys_id>
        <sys_mod_count>0</sys_mod_count>
        <sys_name>x_g_ni4_interdivis_cutoff_date</sys_name>
        <sys_package display_value="Interdivision Work Order" source="x_g_ni4_interdivis">bd43f2a41bc6ac507562a7dcac4bcb29</sys_package>
        <sys_policy/>
        <sys_replace_on_upgrade>false</sys_replace_on_upgrade>
        <sys_scope display_value="Interdivision Work Order">bd43f2a41bc6ac507562a7dcac4bcb29</sys_scope>
        <sys_update_name>ua_table_licensing_config_1efd054d1b2a6c508418ebddac4bcbed</sys_update_name>
        <sys_updated_by>jnz1202</sys_updated_by>
        <sys_updated_on>2021-02-23 18:12:20</sys_updated_on>
    </ua_table_licensing_config>
</record_update>
